fred_mcp/__init__.py
fred_mcp/main.py
fred_mcp/common/__init__.py
fred_mcp/common/types.py
fred_mcp/series/__init__.py
fred_mcp/series/mcp.py
fred_mcp-0.2.0b0.dist-info/licenses/LICENSE
fred_mcp-0.2.0b0.dist-info/METADATA
fred_mcp-0.2.0b0.dist-info/WHEEL
fred_mcp-0.2.0b0.dist-info/entry_points.txt
fred_mcp-0.2.0b0.dist-info/top_level.txt
fred_mcp-0.2.0b0.dist-info/RECORD
