Metadata-Version: 2.4
Name: fred-mcp
Version: 0.2.0b0
Summary: A fully-featured FRED MCP server.
Author-email: Zachary Spar <zachspar@gmail.com>
Project-URL: Homepage, https://github.com/zachspar/fred-mcp
Project-URL: Bug Tracker, https://github.com/zachspar/fred-mcp/issues
Classifier: Development Status :: 4 - Beta
Classifier: Intended Audience :: Developers
Classifier: Intended Audience :: Financial and Insurance Industry
Classifier: Intended Audience :: Science/Research
Classifier: Programming Language :: Python :: 3.10
Classifier: Programming Language :: Python :: 3.11
Classifier: Programming Language :: Python :: 3.12
Classifier: Programming Language :: Python :: 3.13
Classifier: Programming Language :: Python :: 3.14
Classifier: Programming Language :: Python :: 3.15
Classifier: License :: OSI Approved :: MIT License
Classifier: Operating System :: OS Independent
Classifier: Topic :: Scientific/Engineering :: Artificial Intelligence
Requires-Python: >=3.10
License-File: LICENSE
Requires-Dist: fastmcp~=2.3.4
Requires-Dist: fred-py-api~=1.2.0
Dynamic: license-file
